apexapi
